casp/__init__.py
casp/auth.py
casp/cache_handler.py
casp/caspian_config.py
casp/component_decorator.py
casp/components_compiler.py
casp/html_attrs.py
casp/layout.py
casp/loading.py
casp/rpc.py
casp/scripts_type.py
casp/state_manager.py
casp/streaming.py
casp/string_helpers.py
casp/syntax_compiler.py
casp/tw.py
casp/validate.py
caspian_utils-0.0.32.dist-info/METADATA
caspian_utils-0.0.32.dist-info/WHEEL
caspian_utils-0.0.32.dist-info/top_level.txt
caspian_utils-0.0.32.dist-info/RECORD
