Metadata-Version: 2.4
Name: caspian-utils
Version: 0.0.32
Summary: A utility package for Caspian projects
Home-page: https://github.com/TheSteelNinjaCode/caspian_utils
Author: Jefferson Abraham
Classifier: Programming Language :: Python :: 3
Classifier: License :: OSI Approved :: MIT License
Classifier: Operating System :: OS Independent
Requires-Python: >=3.11
Requires-Dist: fastapi~=0.110
Requires-Dist: uvicorn~=0.27
Requires-Dist: python-dotenv~=1.0
Requires-Dist: jinja2~=3.1
Requires-Dist: beautifulsoup4~=4.12
Requires-Dist: tailwind-merge~=0.1
Requires-Dist: slowapi~=0.1
Requires-Dist: python-multipart~=0.0.9
Requires-Dist: starsessions~=1.3
Requires-Dist: httpx~=0.27
Requires-Dist: werkzeug~=3.0
Requires-Dist: cuid2~=2.0
Requires-Dist: nanoid~=2.0
Requires-Dist: python-ulid~=2.7
Dynamic: author
Dynamic: classifier
Dynamic: description
Dynamic: description-content-type
Dynamic: home-page
Dynamic: requires-dist
Dynamic: requires-python
Dynamic: summary
